LICENSE
MANIFEST.in
README.md
config_default.txt
manifest-test.txt
requirements.txt
setup.py
bin/dropbox_uploader.sh
bin/lltk
data/default/CorrectionRules.txt.gz
data/default/spelling_variants_from_morphadorner.txt.gz
data/default/stopwords.onix.txt.gz
data/default/word2pos.json.gz
data/default/wordlist.aspell.net.with_caps.txt.gz
data/etc/CorrectionRules.txt.gz
data/etc/contentwords.byu.txt.gz
data/etc/data.fields.txt.gz
data/etc/spelling_variants_from_morphadorner.txt.gz
data/etc/stopwords.byu.txt.gz
data/etc/stopwords.onix.txt.gz
data/etc/wordlist.aspell.net.with_caps.txt.gz
lltk/__init__.py
lltk/imports.py
lltk/lltk.py
lltk/corpus/__init__.py
lltk/corpus/corpus.py
lltk/corpus/manifest.txt
lltk/corpus/utils.py
lltk/corpus/.ipynb_checkpoints/manifest-checkpoint.txt
lltk/corpus/artfl/README.md
lltk/corpus/artfl/__init__.py
lltk/corpus/artfl/artfl.py
lltk/corpus/artfl/.ipynb_checkpoints/README-checkpoint.md
lltk/corpus/bpo/__init__.py
lltk/corpus/bpo/bpo.py
lltk/corpus/canon_fiction/__init__.py
lltk/corpus/canon_fiction/canon_fiction.py
lltk/corpus/chadwyck/__init__.py
lltk/corpus/chadwyck/chadwyck.py
lltk/corpus/chadwyck_drama/__init__.py
lltk/corpus/chadwyck_drama/chadwyck_drama.py
lltk/corpus/chadwyck_poetry/__init__.py
lltk/corpus/chadwyck_poetry/chadwyck_poetry.py
lltk/corpus/chicago/__init__.py
lltk/corpus/chicago/chicago.py
lltk/corpus/clmet/__init__.py
lltk/corpus/clmet/clmet.py
lltk/corpus/coha/__init__.py
lltk/corpus/coha/coha.py
lltk/corpus/default/__init__.py
lltk/corpus/default/default.py
lltk/corpus/default/new_corpus.py
lltk/corpus/dialnarr/__init__.py
lltk/corpus/dialnarr/dialnarr.py
lltk/corpus/dialogues/__init__.py
lltk/corpus/dialogues/dialogues.py
lltk/corpus/dottxt/__init__.py
lltk/corpus/dottxt/dottxt.py
lltk/corpus/dta/__init__.py
lltk/corpus/dta/dta.py
lltk/corpus/ecco/README.md
lltk/corpus/ecco/__init__.py
lltk/corpus/ecco/ecco.py
lltk/corpus/ecco_tcp/__init__.py
lltk/corpus/ecco_tcp/ecco_tcp.py
lltk/corpus/eebo_tcp/__init__.py
lltk_dh.egg-info/PKG-INFO
lltk_dh.egg-info/SOURCES.txt
lltk_dh.egg-info/dependency_links.txt
lltk_dh.egg-info/requires.txt
lltk_dh.egg-info/top_level.txt