Metadata-Version: 2.1
Name: lltk-dh
Version: 0.5.15
Summary: Literary Language Toolkit (LLTK): corpora, models, and tools for the digital humanities
Home-page: https://github.com/quadrismegistus/lltk
Author: Ryan Heuser
Author-email: rj416@cam.ac.uk
License: MIT
Platform: UNKNOWN
